{
"type": "FeatureCollection",
"name": "bar",
"crs": { "type": "name", "properties": { "name": "urn:ogc:def:crs:OGC:1.3:CRS84" } },
"features": [
{ "type": "Feature", "properties": { "fid": 3, "name": "bar_1", "add:housenumber": null, "add:street": null, "openhour": null, "phone": null }, "geometry": { "type": "Point", "coordinates": [ 33.565237364579481, 60.714968150175622 ] } },
{ "type": "Feature", "properties": { "fid": 1, "name": "Карамболь", "add:housenumber": "14А", "add:street": "ул. Гагарина", "openhour": "11:00-02:00", "phone": "+7 (911) 005-59-35" }, "geometry": { "type": "Point", "coordinates": [ 33.541995308784479, 60.735918080867208 ] } }
]
}
